olxcrapper/olxcrapper.py
olxcrapper-0.1.9.dist-info/LICENSE
olxcrapper-0.1.9.dist-info/METADATA
olxcrapper-0.1.9.dist-info/WHEEL
olxcrapper-0.1.9.dist-info/entry_points.txt
olxcrapper-0.1.9.dist-info/top_level.txt
olxcrapper-0.1.9.dist-info/RECORD
