Metadata-Version: 2.1
Name: olxcrapper
Version: 0.1.9
Summary: Ferramenta de scraping de categorias da OLX com suporte a notificação de novos anúncios pelo GMail
Home-page: https://github.com/yagolimalins/olxcrapper
Author: Yago Lima Lins
Author-email: yago.lima.lins@protonmail.com
License: GPL
Platform: UNKNOWN
Classifier: License :: OSI Approved :: GNU General Public License v3 (GPLv3)
Classifier: Programming Language :: Python :: 3
Classifier: Programming Language :: Python :: 3.8
Requires-Dist: bs4
Requires-Dist: lxml
Requires-Dist: argparse
Requires-Dist: requests
